marksgeometrys/__init__.py
marksgeometrys/geometry.py
marksgeometrys-0.1.1.dist-info/LICENSE.txt
marksgeometrys-0.1.1.dist-info/METADATA
marksgeometrys-0.1.1.dist-info/WHEEL
marksgeometrys-0.1.1.dist-info/top_level.txt
marksgeometrys-0.1.1.dist-info/RECORD
