Metadata-Version: 2.1
Name: marksgeometrys
Version: 0.1.1
Summary: Calculate many figures area or volume
Home-page: https://github.com/marc1fino/marksgeometrys
Author: mark. (Marc Pérez)
Author-email: <marcperezcarrasco2010@gmail.com>
License: MIT
Keywords: python,maths,figures,area,volume,mathematical figures
Classifier: Intended Audience :: Developers
Classifier: Programming Language :: Python :: 3
Classifier: Operating System :: Unix
Classifier: Operating System :: MacOS :: MacOS X
Classifier: Operating System :: Microsoft :: Windows
License-File: LICENSE.txt
